hatch_una/__init__.py
hatch_una/hatch_build.py
hatch_una/hatch_meta.py
hatch_una/py.typed
hatch_una/util.py
hatch_una-0.6.5.dist-info/METADATA
hatch_una-0.6.5.dist-info/WHEEL
hatch_una-0.6.5.dist-info/entry_points.txt
hatch_una-0.6.5.dist-info/RECORD
