Metadata-Version: 2.4
Name: hatch-una
Version: 0.6.5
Summary: Python monorepo tooling
Project-URL: homepage, https://github.com/carderne/una
Project-URL: repository, https://github.com/carderne/una
Author-email: Chris Arderne <chris@rdrn.me>
License: MIT License
Keywords: build,hatch,monorepo,python,uv
Classifier: Environment :: Console
Classifier: Framework :: Hatch
Classifier: Intended Audience :: Developers
Classifier: License :: OSI Approved :: MIT License
Classifier: Operating System :: Unix
Classifier: Programming Language :: Python
Classifier: Programming Language :: Python :: 3.10
Classifier: Programming Language :: Python :: 3.11
Classifier: Programming Language :: Python :: 3.12
Requires-Python: >=3.11
Requires-Dist: hatchling>=1.25.0
